{"success":true,"code":"SUCCESS","message":"Operation completed successfully","data":[{"id":"01c9e7ff","name":"Graph WS c37fef","description":null,"stats":{"thread_count":0,"doc_count":0}},{"id":"d67f597d","name":"Basic WS 25ff3d Updated","description":null,"stats":{"thread_count":0,"doc_count":0}},{"id":"f1e5cefc","name":"RAG WS c9b816","description":null,"stats":{"thread_count":0,"doc_count":0}},{"id":"24f886ce","name":"Conflict Source 282da5","description":null,"stats":{"thread_count":0,"doc_count":1}},{"id":"350969a3","name":"Conflict Target 8d2b1a","description":null,"stats":{"thread_count":0,"doc_count":0}},{"id":"589bcdca","name":"WS 1 3fd14c","description":null,"stats":{"thread_count":1,"doc_count":0}},{"id":"729e034e","name":"WS 2 a52f82","description":null,"stats":{"thread_count":0,"doc_count":0}},{"id":"4e2d3493","name":"Doc WS 1 3edc06","description":null,"stats":{"thread_count":0,"doc_count":0}},{"id":"cd3d921b","name":"Graph WS b88db1","description":null,"stats":{"thread_count":0,"doc_count":0}},{"id":"1c856f07","name":"Basic WS e42cc3 Updated","description":null,"stats":{"thread_count":0,"doc_count":0}},{"id":"66d885e8","name":"RAG WS c0583b","description":null,"stats":{"thread_count":0,"doc_count":0}},{"id":"94558e4d","name":"Conflict Source 52a4a7","description":null,"stats":{"thread_count":0,"doc_count":1}},{"id":"7c903691","name":"Conflict Target 30c787","description":null,"stats":{"thread_count":0,"doc_count":0}},{"id":"f2b225c9","name":"WS 1 ddbd8e","description":null,"stats":{"thread_count":1,"doc_count":0}},{"id":"5a52945b","name":"WS 2 763aee","description":null,"stats":{"thread_count":0,"doc_count":0}},{"id":"65f2a1cc","name":"Doc WS 1 e38d30","description":null,"stats":{"thread_count":0,"doc_count":0}},{"id":"c890edf7","name":"Graph WS aef4f9","description":null,"stats":{"thread_count":0,"doc_count":0}},{"id":"db9a8d96","name":"Basic WS 3c2290 Updated","description":null,"stats":{"thread_count":0,"doc_count":0}},{"id":"82c10563","name":"RAG WS 545d92","description":null,"stats":{"thread_count":0,"doc_count":0}},{"id":"c515d005","name":"Conflict Source 362323","description":null,"stats":{"thread_count":0,"doc_count":1}},{"id":"94991efb","name":"Conflict Target 68ebeb","description":null,"stats":{"thread_count":0,"doc_count":0}},{"id":"4086f8a4","name":"WS 1 237cfc","description":null,"stats":{"thread_count":1,"doc_count":0}},{"id":"dbffbbc3","name":"WS 2 dbfdf6","description":null,"stats":{"thread_count":0,"doc_count":0}},{"id":"58d56a2a","name":"Doc WS 1 1ddfd7","description":null,"stats":{"thread_count":0,"doc_count":0}},{"id":"046b0f27","name":"Graph WS a1fb6f","description":null,"stats":{"thread_count":0,"doc_count":0}},{"id":"929e2d28","name":"Basic WS a9eadf Updated","description":null,"stats":{"thread_count":0,"doc_count":0}},{"id":"200a9f4e","name":"RAG WS 45340c","description":null,"stats":{"thread_count":0,"doc_count":0}},{"id":"020fe782","name":"Conflict Source beca37","description":null,"stats":{"thread_count":0,"doc_count":1}},{"id":"0bec4c2f","name":"Conflict Target afcd89","description":null,"stats":{"thread_count":0,"doc_count":0}},{"id":"55c2f0eb","name":"WS 1 52065c","description":null,"stats":{"thread_count":1,"doc_count":0}},{"id":"5f2da759","name":"WS 2 51396f","description":null,"stats":{"thread_count":0,"doc_count":0}},{"id":"ef23a887","name":"Doc WS 1 e70eb4","description":null,"stats":{"thread_count":0,"doc_count":0}},{"id":"96fd808d","name":"Graph WS dbe1fc","description":null,"stats":{"thread_count":0,"doc_count":0}},{"id":"8a13803d","name":"Basic WS 28001b Updated","description":null,"stats":{"thread_count":0,"doc_count":0}},{"id":"b4b321e5","name":"RAG WS a4d966","description":null,"stats":{"thread_count":0,"doc_count":0}},{"id":"0f09d713","name":"Conflict Source 36aee9","description":null,"stats":{"thread_count":0,"doc_count":1}},{"id":"02e6a164","name":"Conflict Target e40281","description":null,"stats":{"thread_count":0,"doc_count":0}},{"id":"d6f17642","name":"WS 1 b325d0","description":null,"stats":{"thread_count":1,"doc_count":0}},{"id":"4dd67b8b","name":"WS 2 382f2a","description":null,"stats":{"thread_count":0,"doc_count":0}},{"id":"7532ba71","name":"Doc WS 1 855f98","description":null,"stats":{"thread_count":0,"doc_count":0}},{"id":"1892566f","name":"Graph WS f18994","description":null,"stats":{"thread_count":0,"doc_count":0}},{"id":"07480512","name":"Basic WS 5d4878 Updated","description":null,"stats":{"thread_count":0,"doc_count":0}},{"id":"fd4ffddf","name":"RAG WS 204263","description":null,"stats":{"thread_count":0,"doc_count":0}},{"id":"8bf79dd6","name":"Conflict Source 55ed37","description":null,"stats":{"thread_count":0,"doc_count":1}},{"id":"4ed53f52","name":"Conflict Target 7f13b8","description":null,"stats":{"thread_count":0,"doc_count":0}},{"id":"55f4b504","name":"WS 1 5b6a5d","description":null,"stats":{"thread_count":1,"doc_count":0}},{"id":"ee788cf0","name":"WS 2 7757e9","description":null,"stats":{"thread_count":0,"doc_count":0}},{"id":"5e7a64ee","name":"Doc WS 1 fde1aa","description":null,"stats":{"thread_count":0,"doc_count":0}},{"id":"31226a11","name":"Graph WS 07adba","description":null,"stats":{"thread_count":0,"doc_count":0}},{"id":"6206713c","name":"Basic WS a03767 Updated","description":null,"stats":{"thread_count":0,"doc_count":0}},{"id":"1453f206","name":"RAG WS e19ef5","description":null,"stats":{"thread_count":0,"doc_count":0}},{"id":"dabd2ef9","name":"Conflict Source 7ae447","description":null,"stats":{"thread_count":0,"doc_count":1}},{"id":"f4b6b2eb","name":"Conflict Target fbe277","description":null,"stats":{"thread_count":0,"doc_count":0}},{"id":"311387ae","name":"WS 1 4ef200","description":null,"stats":{"thread_count":1,"doc_count":0}},{"id":"9334ad61","name":"WS 2 22be5d","description":null,"stats":{"thread_count":0,"doc_count":0}},{"id":"fff56614","name":"Doc WS 1 0d20df","description":null,"stats":{"thread_count":0,"doc_count":0}},{"id":"db132eb3","name":"Graph WS f57cf3","description":null,"stats":{"thread_count":0,"doc_count":0}},{"id":"a25d560b","name":"Basic WS 778bb8 Updated","description":null,"stats":{"thread_count":0,"doc_count":0}},{"id":"7065e352","name":"RAG WS 40b73b","description":null,"stats":{"thread_count":0,"doc_count":0}},{"id":"1a5e36c7","name":"Conflict Source b9bb38","description":null,"stats":{"thread_count":0,"doc_count":1}},{"id":"8175a1bd","name":"Conflict Target 0b789b","description":null,"stats":{"thread_count":0,"doc_count":0}},{"id":"577eac9b","name":"WS 1 18d58c","description":null,"stats":{"thread_count":1,"doc_count":0}},{"id":"32da5d2f","name":"WS 2 15b3c1","description":null,"stats":{"thread_count":0,"doc_count":0}},{"id":"25d610ca","name":"Doc WS 1 93f5b1","description":null,"stats":{"thread_count":0,"doc_count":0}},{"id":"8f4f77e8","name":"E2E Test Workspace","description":null,"stats":{"thread_count":0,"doc_count":0}}]}